[
  {
    "name": "Poems from a Helper",
    "category": "Poetry",
    "url": "https://www.amazon.com/Audible-Poems-from-a-Helper/dp/B0CXJMWH5D",
    "about": "A collection of poems written over a ten year span extracting emotion and experience from the helping field. Reflections on relationships, pain, death, love, and joy. These poems will delight the mind and the rouse heart.",
    "image": "https://firebasestorage.googleapis.com/v0/b/jeff-talks.appspot.com/o/Poems%20from%20a%20Helper.webp?alt=media&token=03d918f2-50f3-4505-a651-c9d0dc395ab5"
  }
]